BeihangJisuanjiFushiShangjiZhenti20062016/README.md
BeihangJisuanjiFushiShangjiZhenti20062016/__init__.py
BeihangJisuanjiFushiShangjiZhenti20062016/__main__.py
BeihangJisuanjiFushiShangjiZhenti20062016/file.pdf
BeihangJisuanjiFushiShangjiZhenti20062016/index.html
beihang_jisuanji_fushi_shangji_zhenti_2006_2016-2024.3.2.0.dist-info/METADATA
beihang_jisuanji_fushi_shangji_zhenti_2006_2016-2024.3.2.0.dist-info/WHEEL
beihang_jisuanji_fushi_shangji_zhenti_2006_2016-2024.3.2.0.dist-info/entry_points.txt
beihang_jisuanji_fushi_shangji_zhenti_2006_2016-2024.3.2.0.dist-info/top_level.txt
beihang_jisuanji_fushi_shangji_zhenti_2006_2016-2024.3.2.0.dist-info/RECORD
